vilcos/__init__.py
vilcos/app.py
vilcos/auth_utils.py
vilcos/cli.py
vilcos/config.py
vilcos/db.py
vilcos/models.py
vilcos/schemas.py
vilcos/utils.py
vilcos/routes/__init__.py
vilcos/routes/auth.py
vilcos/routes/roles.py
vilcos/routes/users.py
vilcos/routes/websockets.py
vilcos/static/css/main.css
vilcos/static/js/main.js
vilcos/templates/base.html
vilcos/templates/dashboard.html
vilcos/templates/admin/roles.html
vilcos/templates/admin/users.html
vilcos/templates/auth/callback.html
vilcos/templates/auth/signin.html
vilcos/templates/auth/signup.html
vilcos-0.4.0.dist-info/entry_points.txt
vilcos-0.4.0.dist-info/LICENSE
vilcos-0.4.0.dist-info/WHEEL
vilcos-0.4.0.dist-info/METADATA
vilcos-0.4.0.dist-info/RECORD
