Metadata-Version: 2.1
Name: vilcos
Version: 0.4.0
Summary: A FastAPI-based web framework
Author-email: Nidal Alhariri <level09@gmail.com>
Requires-Python: >=3.8
Classifier: Programming Language :: Python :: 3
Classifier: License :: OSI Approved :: MIT License
Classifier: Operating System :: OS Independent
Requires-Dist: fastapi>=0.104.1
Requires-Dist: uvicorn[standard]>=0.24.0
Requires-Dist: jinja2>=3.1.2
Requires-Dist: sqlalchemy>=2.0.23
Requires-Dist: pydantic>=2.5.2
Requires-Dist: pydantic-settings>=2.1.0
Requires-Dist: pydantic-core>=2.14.5
Requires-Dist: python-dotenv>=1.0.0
Requires-Dist: starlette>=0.27.0
Requires-Dist: starlette-session>=0.4.3
Requires-Dist: aioredis>=2.0.1
Requires-Dist: greenlet>=3.0.1
Requires-Dist: asyncpg>=0.29.0
Requires-Dist: typer>=0.9.0
Requires-Dist: IPython>=8.17.2
Requires-Dist: redis>=5.0.1
Requires-Dist: argon2-cffi>=23.1.0
Requires-Dist: email-validator>=2.1.0
Requires-Dist: websockets>=12.0
Project-URL: Home, https://github.com/level09/vilcos
Project-URL: Source, https://github.com/level09/vilcos
